FlexfillsApi/__init__.py
FlexfillsApi/flexfillsapi.py
FlexfillsApi/spec.py
FlexfillsApi-0.2.0.dist-info/LICENSE
FlexfillsApi-0.2.0.dist-info/METADATA
FlexfillsApi-0.2.0.dist-info/WHEEL
FlexfillsApi-0.2.0.dist-info/top_level.txt
FlexfillsApi-0.2.0.dist-info/RECORD
