Metadata-Version: 2.1
Name: FlexfillsApi
Version: 0.2.0
Summary: This package is for using Flex Fills WebSocket communication with FlexFills trading services.
Home-page: https://github.com/Flexfills-UI/Hermes
Author: Djordje Nikolic
Author-email: Djordje Nikolic <magic.guru88@gmail.com>
Project-URL: Homepage, https://github.com/Flexfills-UI/Hermes
Classifier: Programming Language :: Python :: 3
Classifier: License :: OSI Approved :: MIT License
Classifier: Operating System :: OS Independent
Requires-Python: >=3.8
License-File: LICENSE
Requires-Dist: websockets==13.0.1
